LICENSE
README.md
setup.py
blazer/__init__.py
blazer/__version__.py
blazer.egg-info/PKG-INFO
blazer.egg-info/SOURCES.txt
blazer.egg-info/dependency_links.txt
blazer.egg-info/entry_points.txt
blazer.egg-info/not-zip-safe
blazer.egg-info/requires.txt
blazer.egg-info/top_level.txt
blazer/cli/__init__.py
blazer/hpc/__init__.py
blazer/hpc/decorators.py
blazer/hpc/alcf/__init__.py
blazer/hpc/alcf/_cooley.py
blazer/hpc/alcf/_thetagpu.py
blazer/hpc/alcf/then.py
blazer/hpc/gpu/__init__.py
blazer/hpc/gpu/utils.py
blazer/hpc/mpi/__init__.py
blazer/hpc/mpi/primitives.py
blazer/logs/__init__.py
blazer/tests/__init__.py
blazer/tests/funcs.py
blazer/tests/test_parallel.py
blazer/tests/test_pipeline.py