Metadata-Version: 2.1
Name: blazer
Version: 0.1.35
Summary: An HPC abstraction over MPI that uses pipes and pydash primitives for composable super-computing.
Home-page: https://github.com/radiantone/blazer
Author: Darren Govoni
Author-email: darren@ontrenet.com
License: CC0-1.0 License
Keywords: hpc,parallel processing,devops,dataflow,supercomputing,workflows
Platform: UNKNOWN
Classifier: Development Status :: 2 - Pre-Alpha
Classifier: Intended Audience :: Developers
Classifier: Programming Language :: Python :: 3.9
Requires-Python: >=3.8.*
License-File: LICENSE
